{
    "JobId": "523822",
    "JobTitle": "Senior Principal Cloud Software Engineer - Remote, US",
    "JobFullDesc": "Senior Principal Software EngineerRemote in the USA onlyThe Software Engineering team delivers next-generation application enhancements and new products for a changing world. Working at the cutting edge, we design and develop software for platforms, peripherals, applications and diagnostics \u2014 all with the most advanced technologies, tools, software engineering methodologies and the collaboration of internal and external partners.Join us as a Senior Principal Cloud Software Engineeron our Engineering Development team in North America to do the best work of your career and make a profound social impact.ACCOUNTABILITIESUnderstand cloud computing with experience in several technologies including Software as a Service, Infrastructure as a Service, Platform as a Service, Storage as a Service, virtualization computing (VMWare) and cloud delivery models. Experience building and managing cloud technology including workload migrations to the cloud and cloud software development practices and processes. Experience managing Azure, AWS, Google Cloud (GCP) and/or hybrid virtual cloud environments potentially including architecture, design, automation, network engineering, security, storage, systems administration, monitoring, incident response, configuration management, etc. Familiarity with DevOps methods and CI/CD automation practices. Understanding the configuration and/or deployment of containerization technologies and container orchestration (Docker, Kubernetes, etc.)RESPONSIBILITIESLead the development of cloud-based technologies. Quickly demonstrate strong technical leadership through a Proof of Concept (POC) followed by iterative development that delivers scalable, high-performance cloud software services. Ensures high quality software potentially including test driven development. Reviews work-in-progress and suggests strategies to keep projects on schedule.Essential RequirementsGood knowledge of Java and JavaScript and/or Python programming languages; operating systems; databases. Possess a technical knowledge and experience with cloud-based solutions, including systems integrations, preferably with Azure, AWS, Google Cloud (GCP) and/or hybrid virtual private clouds.Desired expertise:1.Experience with cloud configuration management using TerraForm, AWS CloudFormation, Azure RM Templates, Ansible, or similar2.Ability to code/debug and guide others for flexible, scalable and complex programs, using either written or verbal design specifications3.Experience with test automation frameworks4.Ability to learn new tools, languages and operating systems with some training and on-the-job experienceHere\u2019s our story; now tell us yoursDell Technologies helps organizations and individuals build a brighter digital tomorrow. Our company is made up of more than 150,000 people, located in over 180 locations around the world. We\u2019re proud to be a diverse and inclusive team and have an endless passion for our mission to drive human progress.What\u2019s most important to us is that you are respected, feel like you can be yourself and have the opportunity to do the best work of your life -- while still having a life. We offer excellent benefits, bonus programs, flexible work arrangements, a variety of career development opportunities, employee resource groups, and much more.We started with computers, but we didn\u2019t stop there. We are helping customers move into the future with multi-cloud, AI and machine learning through the most innovative technology and services portfolio for the data era. Join us and become a part of what\u2019s next in technology, starting today.You can also learn more about us by reading our latest Diversity and Inclusion Report and our plan to make the world a better place by 2030 here.Dell is committed to the principle of equal employment opportunity for all employees and to providing employees with a work environment free of discrimination and harassment. All employment decisions at Dell are based on business needs, job requirements and individual qualifications, without regard to race, color, religion or belief, national, social or ethnic origin, sex (including pregnancy), age, physical, mental or sensory disability, HIV Status, sexual orientation, gender identity and/or expression, marital, civil union or domestic partnership status, past or present military service, family medical history or genetic information, family or parental status, or any other status protected by the laws or regulations in the locations where we operate. Dell will not tolerate discrimination or harassment based on any of these characteristics. Dell encourages applicants of all ages. Read the full Equal Employment Opportunity Policy here.'cloudbu'",
    "JobPostTime": 1625792566,
    "CompName": "Dell Technologies",
    "CompUrl": "https://powertofly.com/companies/dell-technologies",
    "JobLocation": [
        {
            "@type": "PostalAddress",
            "addressLocality": "",
            "addressRegion": "AR",
            "addressCountry": "US"
        }
    ],
    "Skills": []
}