{
    "JobId": "524058",
    "JobTitle": "Global L&D Learning Design Lead",
    "JobFullDesc": "About the RoleAt Uber, providing world-class support to our partners (riders, drivers and restaurants) is critical to our success. Building the capability of our support teams to consistently deliver elevated levels of service is challenging and sophisticated - and incredibly satisfying!\u00a0We are looking for someone to lead our Global Learning Design team who will oversee an organization that is tasked with designing for multiple learning environments, regions and parts of the Uber business (Eats, Rides, Safety).This multifaceted role requires strong program and people leadership skills, specialist planning & organization, creativity and expertise in adult learning, storytelling, and UX Learning Design to support the organization in executing on complex strategic global design projects.\u00a0What You\u2019ll DoThe Global design strategy and resources are key to supporting the CommOps business and driving efficient and effective learning solutions across our COE, GL and vendor environments globally.You will be responsible for developing the organization, designers, and processes to provide design solutions for Global Community Operations L&D.You will be tasked with leading and creating all standard global processes for design and ensuring continued alignment amongst our organization.Basic QualificationsDegree qualified in Learning design, Education or other relevant fields (Masters preferred, Bachelors minimum)Demonstrated ability leading Global Design functions and teams (10 years) ; consistent track record of leading teams of 5+ at a global level to deliver scalable learning solutionsStrong project management skills with outstanding organizational, time management, and prioritization skillsStrong written, verbal, and visual interpersonal skills, and validated ability to influence and drive consensus at senior levelsStrategic thinking and ability to bring stakeholders across multiple geographies and functions togetherExpertise in Adult Learning Theory and instructional design principles.Experience working in an agile (SAM) and/or waterfall (ADDIE) design environment.Preferred QualificationsMaster's degree in relevant fieldDeep expertise and experience in Learning DesignExperience in content authoring, rapid design tools, UX, or visual/graphic design.Background/Experience in Camtasia, Vyond, Figma, Canva, etc.Experience in UX and visual/graphic design.",
    "JobPostTime": 1625792638,
    "CompName": "Uber",
    "CompUrl": "https://powertofly.com/companies/uber",
    "JobLocation": [
        {
            "@type": "PostalAddress",
            "addressLocality": "Chicago",
            "addressRegion": "IL",
            "addressCountry": "US"
        }
    ],
    "Skills": []
}