{
    "JobId": "525548",
    "JobTitle": "Senior Front End Architect",
    "JobFullDesc": "You think about how experiences connected to the broader architectural picture. You are an experienced architect that has an established track record-breaking down complex problems into smaller, composable parts. You are able to communicate at leadership levels and communicate complex software architecture with the best of architects. You are an expert at applying platform features and best practices and sharing that knowledge to help the team grow.  You bring:  7+ years of software engineering experience working with web or mobile web tools/frameworks and interacting with vendor and microservice APIs  Ability to understand and abstract requirements and identify right technologies for building large scale technologies  Experience evaluating and architecting technologies for attributes such as scalability, feasibility, flexibility, and ability to accelerate the work that we do for our clients  Ability to clearly communicate technical decisions and tradeoffs to clients and project stakeholders  Must be legally authorized to work in the United States without the need for employer sponsorship, now or at any time in the future  Work you'll do:  Develop cutting-edge web applications that perform superbly across all platforms.  Work in a highly collaborative environment with cross-functional teams on projects ranging from a few weeks to a few months in length.  Clearly and concisely communicate highly technical challenges and solutions to clients and non-technical team members. Maintain a high standard of quality as you creatively and strategically problem solve throughout the product delivery process.  Be able to effectively communicate your work with both technical and non-technical peers Be excited about new web technologies/techniques  Build solid back-end architectures that integrate easily with other systems and technologies Understand design patterns and write reusable, modular code  Love working closely with other disciplines (Front-end, UX, Design, QA)  Have superior attention to detail and a strong ability to Q/A one ' sown work required, including cross-browser and cross-platform displays and performance  The Deloitte Studios Team  Sits within our \"Advertising, Marketing & Commerce\" offering Within our group, we create content, communications, and experiences that engage and inspire our clients' customers to act. We implement and operate the technology platforms that enable personalized content, commerce and user-centric experiences. And, in doing so, we transform our clients' marketing and engagement operations into modern, data-driven, creatively focused organizations - all built to drive growth. Our AM&C offering serves our clients through the following types of work:  Cross-channel customer engagement strategy, design and development to include the creation of omni-channel digital experiences across web, mobile, social, physical, AR/VR, voice, gesture, IoT, and video  eCommerce strategy, implementation and operations  Marketing Content and digital asset management solutions  Marketing Technology and Advertising Technology solutions  Marketing analytics implementation and operations  Advertising campaign ideation, development and execution  Acquisition and engagement campaign ideation, development and execution  Agile based, design-thinking, user-centric, empirical projects that accelerate results  Bonus points for:  A willingness to participate in the sales process including limited travel  Experience working in a consulting environment  Experience working with globally distributed teams  Participation in the open-source community For individuals assigned and/or hired to work in Colorado, Deloitte is required by law to include a reasonable estimate of the compensation range for this role. This compensation range is specific to the State of Colorado and takes into account the wide range of factors that are considered in making compensation decisions including but not limited to skill sets; experience and training; licensure and certifications; and delivery model. We would not anticipate that the individual hired into this role would land at or near the top end of the range, but such a decision will be dependent on the facts and circumstances of each case. A reasonable estimate of the range is $138,000 to $184,000. You may also be eligible to participate in a discretionary annual incentive program, subject to the rules governing the program, whereby an award, if any, depends on various factors, including, without limitation, individual and organizational performance. kwdeldigallddusa  kwdeldigdesignusa  kwdeldigengineerusa  deloittestudios  AMC2021  #LI-CONS #IND:CONS",
    "JobPostTime": 1625828652,
    "CompName": "Deloitte LLP",
    "CompUrl": "https://powertofly.com/companies/deloitte1",
    "JobLocation": [
        {
            "@type": "PostalAddress",
            "addressLocality": "",
            "addressRegion": "",
            "addressCountry": "US"
        }
    ],
    "Skills": []
}