{
    "JobId": "526025",
    "JobTitle": "Principal PM Manager",
    "JobFullDesc": "As the fastest growing business application in Microsoft\u2019s history, Teams is redefining how our customers collaborate and communicate in their environments. Teams addresses the needs of a diverse workforce by providing a hub for collaboration. It brings together multiple communication methods of chat, messaging, calling, and meetings, along with document collaboration, plus third-party and custom line-of-business apps.As customers rely on Teams for their business-critical collaboration, their needs around privacy, safety, security, and compliance continue to grow. We have a responsibility to help keep our customers safe and, in partnership with security product groups both within and outside Microsoft, we have an opportunity to truly differentiate Teams as the most secure and trustworthy collaboration platform. We are looking for a self-starting, entrepreneurial Principal Program Manager Lead who will manage a team to shape the future of secure and trustworthy collaboration in Teams.We are a dynamic and agile team in the Microsoft Teams product group. We have an open, respectful, and empowering culture, and you will have plenty of opportunity to work directly with our customers and leadership.ResponsibilitiesManage, mentor, and lead a team of highly skilled Program Managers to envision and deliver our feature roadmap to ultimately achieve our objectives.Establish the objectives and product strategy to deliver business growth in this space.Develop a deep understanding of customer needs and challenges, competitive pressures, and business opportunity. Be the voice of the customer.Partner with other product teams across Microsoft to ensure strategy and execution alignment.Provide product and technical leadership in partnership with a team of highly passionate engineers. Drive clarity by writing papers, developing experiences, and writing specs that will illustrate the opportunity, develop the plan, and keep our team and our partner teams on the same pageQualificationsMicrosoft is an equal opportunity employer. All qualified applicants will receive consideration for employment without regard to age, ancestry, color, family or medical care leave, gender identity or expression, genetic information, marital status, medical condition, national origin, physical or mental disability, political affiliation, protected veteran status, race, religion, sex (including pregnancy), sexual orientation, or any other characteristic protected by applicable laws, regulations and ordinances.\u00a0If you need assistance and/or a reasonable accommodation due to a disability during the application or the recruiting process, please send a request\u00a0via the Accommodation request form.\u00a0Benefits/perks listed below may vary depending on the nature of your employment with Microsoft and the country where you work.\u00a0\u00a0Bachelor's Degree along with degree or equivalent experience in Engineering, Computer Science, or Mathematics. Supplemental business degrees (such as an MBA) a bonus.8+years of product management, product design, customer empathy, and creative problem solving3+ years of people management experienceExceptional ability to negotiate and collaborate across teams and organizationsRelentless focus on creating the best possible user experiencesPride in ownership and personal accountability for your product end-to-endProactive and tenacious drive for results with a sense of urgencyStrong technical aptitude, data focus, and analytical skillsAbility to handle significant ambiguity and rapid change",
    "JobPostTime": 1625847196,
    "CompName": "Microsoft Corporation",
    "CompUrl": "https://powertofly.com/companies/microsoft-corporation",
    "JobLocation": [
        {
            "@type": "PostalAddress",
            "addressLocality": "Bangalore",
            "addressRegion": "KA",
            "addressCountry": "IN"
        }
    ],
    "Skills": []
}