{
    "JobId": "478272",
    "JobTitle": "Automation Specialist AMER, Premier Partner Protection",
    "JobFullDesc": "The Premier Partner Protection team develops solutions for partners by creating scaled systems to address issues impacting their experiences with the suite of Facebook products. Within Partner Operations, the Partner Protection team protects users and ensures safe connections between Media constituents and their followers. We do so by understanding the landscape, identifying and analyzing problems and trends, and executing scalable solutions. We partner with engineering and other integrity teams to drive solutions.Develop a deep understanding of issues facing our constituents and how it affects Facebook, Instagram and our communitiesImplement effective anti-fraud automations to eliminate abusive behaviors, based on identified risksAnalyze and interpret data in order to devise hypotheses on how fraudulent and other nefarious activity is proliferatingCommunicating to technical/non-technical audiencesRequires contributing to Facebook\u2019s anti-abuse codebaseEstablish short and long-term goals that will advance the organization\u2019s impact through data and analyticsProactively  investigate, troubleshoot, and resolve sensitive escalationsWork collaboratively with cross-functional stakeholders including but not limited to Policy, Communications, Escalations, Spam and other operations teams to solve problems at scaleWeekend and holiday work on a shift basisMINIMUM QUALIFICATIONSBachelor's degree in Business, Science, Engineering, Economics or equivalent practical experienceExperience manipulating large data sets in SQL or equivalentExperience in at least one scripting language (PHP, Python, Perl), statistical software (R, SAS, SPSS), or data visualization tool (Tableau)2+ years of work experience in an abuse, investigations, consulting, or online operations environmentPREFERRED QUALIFICATIONSBachelor's degree in Business, Science, Engineering, Economics or equivalent practical experienceExperience manipulating large data sets in SQL or equivalentExperience in at least one scripting language (PHP, Python, Perl), statistical software (R, SAS, SPSS), or data visualization tool (Tableau)2+ years of work experience in an abuse, investigations, consulting, or online operations environmentFacebook's mission is to give people the power to build community and bring the world closer together. Through our family of apps and services, we're building a different kind of company that connects billions of people around the world, gives them ways to share what matters most to them, and helps bring people closer together. Whether we're creating new products or helping a small business expand its reach, people at Facebook are builders at heart. Our global teams are constantly iterating, solving problems, and working together to empower people around the world to build community and connect in meaningful ways. Together, we can help people build stronger communities - we're just getting started.",
    "JobPostTime": 1625933189,
    "CompName": "Facebook, Inc.",
    "CompUrl": "https://powertofly.com/companies/facebook-inc",
    "JobLocation": [
        {
            "@type": "PostalAddress",
            "addressLocality": "Sunnyvale",
            "addressRegion": "CA",
            "addressCountry": "US"
        }
    ],
    "Skills": []
}