{
    "JobId": "523947",
    "JobTitle": "Account Representative / Account Executive - North New Jersey",
    "JobFullDesc": "What You'll DoLeverage prospecting skills and relationships to build partnerships with merchants in your geographic regionManage contract negotiations aimed at establishing the foundation of a strong working relationship with our merchants, including sustainable economics for both partiesClearly communicate the value of Uber and its newest products to prospectsAchieve and consistently exceed monthly targetsPartner with our Operations and Account Managers to smoothly activate the best merchantsHelp us identify and build best practicesDevelop long-term relationships with key in-region partners\u00a0Act as an ambassador of Uber Eats' mission, brand, and productProactively maintain communication channels with prospects via email, phone, and face-to-face meetingsBasic QualificationsFor Account Representative - At least 1 year of experience in sales, operations, account management, or similar functionsFor Account Executive - At least 3 year of experience in sales, operations, account management, or similar functionsPreferred QualificationsProficiency in SalesforceOutstanding work ethic and attention to detailWillingness to roll up your sleeves, and get in the weeds with our highest value partnersExcellent communication and sales skillsStrong critical thinking ability",
    "JobPostTime": 1625792599,
    "CompName": "Uber",
    "CompUrl": "https://powertofly.com/companies/uber",
    "JobLocation": [
        {
            "@type": "PostalAddress",
            "addressLocality": "Newark",
            "addressRegion": "NJ",
            "addressCountry": "US"
        }
    ],
    "Skills": []
}