{
    "JobId": "526484",
    "JobTitle": "Account Representative, Uber Eats",
    "JobFullDesc": "What You'll DoThis role is based in Chicago but will be selling into markets across the Midwest, such as Minneapolis, Kansas City and/or St. LouisWhen corporate travel resumes, sellers should expect to spend 4 days per month in MarketLeverage prospecting skills and relationships to build partnerships with merchants in your geographic territoryManage contract negotiations aimed at establishing the foundation of a strong working relationship with our merchants, including sustainable economics for both partiesClearly communicate the value of Uber and its newest products to prospectsAchieve and consistently exceed monthly targetsPartner with our Operations and Account Managers to smoothly activate the best merchantsHelp us identify and build best practicesDevelop long-term relationships with key in-region partnersAct as an ambassador of Uber Eats' mission, brand, and productProactively maintain communication channels with prospects via email, phone, and face-to-face meetingsField sales is an expectation for this roleBasic QualificationsFor Account Representative - At least 1 year of experience in sales, operations, account management, or similar functionsFor Account Executive - At least 3 year of experience in sales, operations, account management, or similar functionsPreferred QualificationsProficiency in SalesforceOutstanding work ethic and attention to detailWillingness to roll up your sleeves, and get in the weeds with our highest value partnersExcellent communication and sales skillsStrong critical thinking abilityAveraging a minimum of 6 CW per week for the past 4 weeks for ramped sellers (3+ months)",
    "JobPostTime": 1625914828,
    "CompName": "Uber",
    "CompUrl": "https://powertofly.com/companies/uber",
    "JobLocation": [
        {
            "@type": "PostalAddress",
            "addressLocality": "Chicago",
            "addressRegion": "IL",
            "addressCountry": "US"
        }
    ],
    "Skills": []
}