{
    "JobId": "523991",
    "JobTitle": "Corporate Development Associate/Senior Associate",
    "JobFullDesc": "In Finance, we work hand-in-hand with leaders across the company to ensure smooth, disciplined execution of strategic business objectives. In this team, you\u2019ll lead Uber\u2019s efforts across M&A and capital markets, and serve as the primary interface to many of the Company\u2019s investors.About the RoleYou will serve as a key member of the Uber Corporate Development team, supporting our inorganic efforts across all business lines globally. You will have the opportunity to work on a high-performing team that has a major impact on the direction of the Company as well as with senior leadership at Uber.What You'll DoDevelop Uber\u2019s M&A strategy and identify transaction opportunities in concert with business leadership across Mobility, Delivery, and FreightSupport the entirety of the M&A process including strategy, sourcing, diligence, negotiation, and executionConduct thorough financial analysis to assess company valuation and synergy opportunitiesPrepare and give business reviews to Uber\u2019s executive leadership team regarding progress and roadblocksSupport public and private market capital raising transactionsBasic Qualifications2+ years of experience in investment banking, private equity, venture capital management consulting, or corporate development at a technology company or similar experienceBS/BA degree or equivalentPreferred QualificationsStrong quantitative and qualitative analytical skills including financial and company valuation analysesThe ability to excel across a wide variety of work (strategy, sourcing, analysis, negotiation, and integration)A track record of sophisticated problem solving, attention to detail, and delivering results cross-functionallyOutstanding interpersonal skills, business judgment, and crisp communicationAdaptability to change within a fast paced corporate environment and numerous transaction opportunities",
    "JobPostTime": 1625792620,
    "CompName": "Uber",
    "CompUrl": "https://powertofly.com/companies/uber",
    "JobLocation": [
        {
            "@type": "PostalAddress",
            "addressLocality": "San Francisco",
            "addressRegion": "CA",
            "addressCountry": "US"
        }
    ],
    "Skills": []
}