{
    "JobId": "526275",
    "JobTitle": "Purple Team Data Analyst",
    "JobFullDesc": "AssociateMorgan Stanley is a leading global financial services firm providing a wide range of investment banking, securities, investment management and wealth management services. The Firm's employees serve clients worldwide including corporations, governments and individuals from more than 1,200 offices in 43 countries. As a market leader, the talent and passion of our people is critical to our success. Together, we share a common set of values rooted in integrity, excellence and strong team ethic. Morgan Stanley can provide a superior foundation for building a professional career - a place for people to learn, to achieve and grow. A philosophy that balances personal lifestyles, perspectives and needs is an important part of our culture. \nTechnology works as a strategic partner with Morgan Stanley business units and the world's leading technology companies to redefine how we do business in ever more global, complex, and dynamic financial markets. Morgan Stanley's sizeable investment in technology results in quantitative trading systems, cutting-edge modeling and simulation software, comprehensive risk and security systems, and robust client-relationship capabilities, plus the worldwide infrastructure that forms the backbone of these systems and tools. Our insights, our applications and infrastructure give a competitive edge to clients' businesses\u2014and to our own.\nThe Morgan Stanley Purple Team\u2019s responsibility is to perform security assessments and attack surface discovery at scale that improve the Firm\u2019s ability to detect, prevent, and respond to threats. The team accomplishes this primarily by executing Advanced Persistent Threat (APT) scenarios designed to challenge and improve the response, analytics, and hunting functions at the Firm with a cooperative ethos.\n\nTo ensure our work results in defensive improvements as fast as possible, we sit alongside Security Response Teams - Incident Response (IR) and Security Operations Center (SOC), collaborating with team members from both daily. Together, IR and SOC oversee a 24/7 operation with members in key geographical locations that perform incident response and remediation, campaign assessments, as well as network and host-based forensics; our team is committed to supporting continual improvement of Blue Team operations.\nResponsibilities:\nYou will be responsible for executing Purple Team\u2019s Attack Surface Discovery strategy to best employ of a portfolio of technology platforms that enable the discovery of attack vectors and/or security weaknesses within the Firm\u2019s estate. You will bring the program to the next level by leveraging your unique abilities to drive improvements in the processing and analysis of large, disparate data sets to develop analytics and reporting of value.\n\nYou will help ensure Vulnerability Management stakeholders possess the right data before they need it and will support the new Breach and Attack Simulations program as it is further developed and integrated into Firm processes. This work will be a blend of elements of operations, data science, and data analysis. Additionally, you will assist in scanning and oversight of third-party reputation management services, coordinating remediation of issues that may arise.\n",
    "JobPostTime": 1625863508,
    "CompName": "Morgan Stanley Technology",
    "CompUrl": "https://powertofly.com/companies/morgan-stanley-technology",
    "JobLocation": [
        {
            "@type": "PostalAddress",
            "addressLocality": "Baltimore",
            "addressRegion": "MD",
            "addressCountry": "US"
        }
    ],
    "Skills": []
}