{
    "JobId": "402257",
    "JobTitle": "AVP/VP \u2013 Regulatory Analyst (Climate)",
    "JobFullDesc": "Department \n\nMoody\u2019s ESG Solutions Group (MESGS) is a business unit of Moody\u2019s Corporation serving the growing global demand for ESG and climate insights. The group leverages Moody\u2019s data and expertise across ESG, climate risk, and sustainable finance, and aligns with Moody's Investors Service (MIS) and Moody's Analytics (MA) to deliver a comprehensive, integrated suite of ESG and climate risk solutions including ESG scores, analytics, Sustainability Ratings and Sustainable Finance Reviewer/certifier services. It houses V.E and 427, both affiliates of Moody\u2019s.#LI-SG1 Job Description\n\nThe Role Responsible for critical impact assessments of global regulatory and policy developments related to climate risk disclosures, climate stress tests and the Task Force on Climate-Related Financial Disclosures (TCFD) on Moody\u2019s suite of products and methodological frameworks.Ensure that key stakeholders at Moody\u2019s are kept informed pro-actively and rigorously of key developments related to climate risk to inform product development, methodology design and sales strategy.Responsibilities:Analytics/MonitoringAnalyze relevant regulatory and market developments related to climate risk and perform gap analysis and impact assessment to identify where Moody\u2019s offerings may need to be adjusted or expanded to meet requirements laid out by regulators and key industry groups Distil regulations and industry guidance into consolidated technical market requirementsCommunicate pro-actively with relevant teams across analytics, products, marketing and sales to articulate the implications of new regulatory developments related to climate riskAct as a resource for the different functions, organize trainings and create supporting documentation Engagement with Regulators and Key StakeholdersParticipate in internal and external outreach events to present regulatory analysisAttend and represent Moody\u2019s in stakeholder meetings, webinars and conferences and bilateral meetings, share key findings with relevant functions.Contribute as a subject matter expert in responses to third party consultations on topics related to climate risk and ESG regulations, coordinate information gathering across the organizations where multiple groups are involved QualificationsUndergraduate/first-level degree (e.g., Bachelor's degree) in a related discipline (e.g., public affairs, political science, law, business, sustainability), graduate/second-level degree preferred.Proficient in interpretation of relevant accounting standards (preferred)3-7 years of relevant experience, including significant exposure to banking regulationDemonstrated proficiency on the topic of climate risk for the financial sector An analytical mind, able to identify strategic developments Articulate and succinct written and verbal communication skills Rigorous, attention to detailsStrong organizational skills with sound judgmentAbility to work effectively in a collaborative team environment.Ability to adapt to a changing environment and prioritize tasks accordingly, independently balancing conflicting priorities.",
    "JobPostTime": 1625846551,
    "CompName": "Moody's Corporation",
    "CompUrl": "https://powertofly.com/companies/moody-s-corporation",
    "JobLocation": [
        {
            "@type": "PostalAddress",
            "addressLocality": "",
            "addressRegion": "",
            "addressCountry": "US"
        }
    ],
    "Skills": []
}